README.md
setup.cfg
setup.py
pydbpedia/__init__.py
pydbpedia/namespace.py
pydbpedia/pyDBpedia.py
pydbpedia.egg-info/PKG-INFO
pydbpedia.egg-info/SOURCES.txt
pydbpedia.egg-info/dependency_links.txt
pydbpedia.egg-info/requires.txt
pydbpedia.egg-info/top_level.txt