Metadata-Version: 1.2
Name: pydbpedia
Version: 0.0.1
Summary: pyDBpedia is a simple python wrapper for querying dbpedia
Home-page: https://github.com/MatteusT/pyDBpedia
Author: Matteus Tanha
Author-email: matteus.tanha@gmail.com
License: Apache 2.0
Download-URL: https://github.com/MatteusT/pyDBpedia/archive/v0.0.1.tar.gz
Keywords: DBpedia,knowledge base
Platform: UNKNOWN
Classifier: Development Status :: 3 - Alpha
Classifier: Intended Audience :: Developers
Classifier: Topic :: Software Development :: Libraries :: Python Modules
Classifier: License :: OSI Approved :: Apache Software License
Classifier: Programming Language :: Python
Classifier: Programming Language :: Python :: 3.6
Classifier: Programming Language :: Python :: 3.7
Classifier: Operating System :: OS Independent
Classifier: Natural Language :: English
Requires-Python: >=3.6
